{
  "title": "interact.js",
  "output": "tmp/npm/api/index.html.erb",
  "template": "api-template.dot",
  "files": [
    {
      "url": "interactjs/src/actions/drag.js",
      "link": "https://github.com/taye/interact.js/blob/{VERSION}/src/actions/drag.js"
    },
    {
      "url": "interactjs/src/actions/drop.js",
      "link": "https://github.com/taye/interact.js/blob/{VERSION}/src/actions/drop.js"
    },
    {
      "url": "interactjs/src/actions/resize.js",
      "link": "https://github.com/taye/interact.js/blob/{VERSION}/src/actions/resize.js"
    },
    {
      "url": "interactjs/src/actions/gesture.js",
      "link": "https://github.com/taye/interact.js/blob/{VERSION}/src/actions/gesture.js"
    },
    {
      "url": "interactjs/src/Interactable.js",
      "link": "https://github.com/taye/interact.js/blob/{VERSION}/src/Interactable.js"
    },
    {
      "url": "interactjs/src/autoStart/base.js",
      "link": "https://github.com/taye/interact.js/blob/{VERSION}/src/autoStart/base.js"
    },
    {
      "url": "interactjs/src/interactablePreventDefault.js",
      "link": "https://github.com/taye/interact.js/blob/{VERSION}/src/interactablePreventDefault.js"
    },
    {
      "url": "interactjs/src/interact.js",
      "link": "https://github.com/taye/interact.js/blob/{VERSION}/src/interact.js"
    },
    {
      "url": "interactjs/src/Interaction.js",
      "link": "https://github.com/taye/interact.js/blob/{VERSION}/src/Interaction.js"
    }
  ]
}
